roarm_sdk/__init__.py
roarm_sdk/common.py
roarm_sdk/generate.py
roarm_sdk/logger.py
roarm_sdk/roarm.py
roarm_sdk/utils.py
roarm_sdk-0.0.13.dist-info/LICENSE
roarm_sdk-0.0.13.dist-info/METADATA
roarm_sdk-0.0.13.dist-info/WHEEL
roarm_sdk-0.0.13.dist-info/top_level.txt
roarm_sdk-0.0.13.dist-info/RECORD
